{
  "note": "High-frequency Italian starter deck, ordered by rough frequency rank. A later data task expands this toward the top 2–3k word families.",
  "words": [
    { "it": "essere",     "en": "to be",          "ex": "Voglio essere felice." },
    { "it": "avere",      "en": "to have",        "ex": "Ho una buona idea." },
    { "it": "fare",       "en": "to do / make",   "ex": "Cosa vuoi fare oggi?" },
    { "it": "dire",       "en": "to say",         "ex": "Devo dire la verità." },
    { "it": "potere",     "en": "to be able to",  "ex": "Non posso venire stasera." },
    { "it": "volere",     "en": "to want",        "ex": "Voglio un caffè." },
    { "it": "sapere",     "en": "to know",        "ex": "Non so dove sia." },
    { "it": "andare",     "en": "to go",          "ex": "Vado a casa adesso." },
    { "it": "vedere",     "en": "to see",         "ex": "Ci vediamo domani." },
    { "it": "venire",     "en": "to come",        "ex": "Vieni con me?" },
    { "it": "dare",       "en": "to give",        "ex": "Mi dai una mano?" },
    { "it": "stare",      "en": "to stay / be",   "ex": "Come stai?" },
    { "it": "dovere",     "en": "to have to",     "ex": "Devo studiare stasera." },
    { "it": "parlare",    "en": "to speak",       "ex": "Parli italiano?" },
    { "it": "trovare",    "en": "to find",        "ex": "Non trovo le chiavi." },
    { "it": "casa",       "en": "house / home",   "ex": "Torno a casa tardi." },
    { "it": "tempo",      "en": "time / weather", "ex": "Non ho tempo oggi." },
    { "it": "giorno",     "en": "day",            "ex": "Che bel giorno!" },
    { "it": "anno",       "en": "year",           "ex": "Ho trent'anni." },
    { "it": "uomo",       "en": "man",            "ex": "Quell'uomo è alto." },
    { "it": "donna",      "en": "woman",          "ex": "La donna legge un libro." },
    { "it": "vita",       "en": "life",           "ex": "La vita è bella." },
    { "it": "mano",       "en": "hand",           "ex": "Ho le mani fredde." },
    { "it": "occhio",     "en": "eye",            "ex": "Ha gli occhi verdi." },
    { "it": "acqua",      "en": "water",          "ex": "Vorrei un po' d'acqua." },
    { "it": "cibo",       "en": "food",           "ex": "Il cibo è ottimo qui." },
    { "it": "amico",      "en": "friend",         "ex": "Lui è il mio amico." },
    { "it": "lavoro",     "en": "work / job",     "ex": "Vado al lavoro presto." },
    { "it": "città",      "en": "city",           "ex": "Roma è una grande città." },
    { "it": "bambino",    "en": "child",          "ex": "Il bambino dorme." },
    { "it": "grande",     "en": "big / great",    "ex": "È una grande occasione." },
    { "it": "piccolo",    "en": "small",          "ex": "Un piccolo problema." },
    { "it": "nuovo",      "en": "new",            "ex": "Ho una macchina nuova." },
    { "it": "buono",      "en": "good",           "ex": "Questo caffè è buono." },
    { "it": "bello",      "en": "beautiful",      "ex": "Che bella giornata!" },
    { "it": "primo",      "en": "first",          "ex": "È la prima volta." },
    { "it": "ultimo",     "en": "last",           "ex": "L'ultimo treno è partito." },
    { "it": "molto",      "en": "very / a lot",   "ex": "Mi piace molto." },
    { "it": "poco",       "en": "little / few",   "ex": "Ho poco tempo." },
    { "it": "sempre",     "en": "always",         "ex": "Arrivo sempre tardi." },
    { "it": "mai",        "en": "never",          "ex": "Non lo faccio mai." },
    { "it": "oggi",       "en": "today",          "ex": "Oggi piove." },
    { "it": "domani",     "en": "tomorrow",       "ex": "A domani!" },
    { "it": "adesso",     "en": "now",            "ex": "Lo faccio adesso." },
    { "it": "qui",        "en": "here",           "ex": "Vieni qui!" },
    { "it": "bene",       "en": "well",           "ex": "Tutto bene?" },
    { "it": "anche",      "en": "also / too",     "ex": "Vengo anch'io." },
    { "it": "perché",     "en": "why / because",  "ex": "Perché non mangi?" },
    { "it": "grazie",     "en": "thank you",      "ex": "Grazie mille!" },
    { "it": "ciao",       "en": "hi / bye",       "ex": "Ciao, come va?" }
  ]
}
